nnfe/__init__.py
nnfe/aggregation.py
nnfe/cli.py
nnfe/neighbor.py
nnfe/nnfe.py
nnfe-0.2.1.dist-info/LICENSE
nnfe-0.2.1.dist-info/METADATA
nnfe-0.2.1.dist-info/WHEEL
nnfe-0.2.1.dist-info/entry_points.txt
nnfe-0.2.1.dist-info/top_level.txt
nnfe-0.2.1.dist-info/RECORD
