Metadata-Version: 2.1
Name: nnfe
Version: 0.2.1
Summary: Nearest Neighbor Feature Extraction
Home-page: https://github.com/haroldmei/nnfe
Author: Haiyuan Mei
Author-email: haroldmei.cn@gmail.com
License: MIT license
Keywords: nnfe
Classifier: Development Status :: 2 - Pre-Alpha
Classifier: Intended Audience :: Developers
Classifier: License :: OSI Approved :: MIT License
Classifier: Natural Language :: English
Classifier: Programming Language :: Python :: 3
Classifier: Programming Language :: Python :: 3.6
Classifier: Programming Language :: Python :: 3.7
Classifier: Programming Language :: Python :: 3.8
Requires-Python: >=3.6
License-File: LICENSE
